hunabku_scienti/__init__.py
hunabku_scienti/_version.py
hunabku_scienti/endpoints/Scienti.py
Hunabku_scienti-0.0.10.dist-info/LICENSE
Hunabku_scienti-0.0.10.dist-info/METADATA
Hunabku_scienti-0.0.10.dist-info/WHEEL
Hunabku_scienti-0.0.10.dist-info/top_level.txt
Hunabku_scienti-0.0.10.dist-info/RECORD
