Metadata-Version: 2.1
Name: Hunabku-scienti
Version: 0.0.10
Summary: Hunabku scienti plugin
Home-page: https://github.com/colav/Hunabku_plugins
Author: Colav
Author-email: colav@udea.edu.co
License: BSD
License-File: LICENSE
Requires-Dist: flask >=1.1.2
Requires-Dist: requests >=2.22.0
Requires-Dist: hunabku
Requires-Dist: pymongo
Requires-Dist: elasticsearch >=7.0.0
Requires-Dist: elasticsearch-dsl >=7.0.0
